CHANGES.txt
LICENSE-Pyramid.txt
LICENSE.txt
MANIFEST.in
README.md
TESTING.txt
TODO.txt
pyproject.toml
setup.cfg
setup.py
tox.ini
src/pyramid_oauthlib_lowlevel/__init__.py
src/pyramid_oauthlib_lowlevel/errors.py
src/pyramid_oauthlib_lowlevel/py.typed
src/pyramid_oauthlib_lowlevel/utils.py
src/pyramid_oauthlib_lowlevel.egg-info/PKG-INFO
src/pyramid_oauthlib_lowlevel.egg-info/SOURCES.txt
src/pyramid_oauthlib_lowlevel.egg-info/dependency_links.txt
src/pyramid_oauthlib_lowlevel.egg-info/not-zip-safe
src/pyramid_oauthlib_lowlevel.egg-info/requires.txt
src/pyramid_oauthlib_lowlevel.egg-info/top_level.txt
src/pyramid_oauthlib_lowlevel/client/__init__.py
src/pyramid_oauthlib_lowlevel/client/api_client.py
src/pyramid_oauthlib_lowlevel/oauth1/__init__.py
src/pyramid_oauthlib_lowlevel/oauth1/errors.py
src/pyramid_oauthlib_lowlevel/oauth1/provider.py
src/pyramid_oauthlib_lowlevel/oauth1/utils.py
src/pyramid_oauthlib_lowlevel/oauth1/validator.py
src/pyramid_oauthlib_lowlevel/oauth2/__init__.py
src/pyramid_oauthlib_lowlevel/oauth2/errors.py
src/pyramid_oauthlib_lowlevel/oauth2/provider.py
src/pyramid_oauthlib_lowlevel/oauth2/validator.py
tests/__init__.py
tests/_utils.py
tests/oauth1_model.py
tests/oauth1_utils.py
tests/oauth2_model.py
tests/oauth2_utils.py
tests/test_oauth1.py
tests/test_oauth2.py
tests/oauth1_app/__init__.py
tests/oauth1_app/views.py
tests/oauth1_app/model/__init__.py
tests/oauth1_app/templates/authorize-error.mako
tests/oauth1_app/templates/authorize-form.mako
tests/oauth2_app/__init__.py
tests/oauth2_app/views.py
tests/oauth2_app/model/__init__.py
tests/oauth2_app/templates/authorize-error.mako
tests/oauth2_app/templates/authorize-form.mako