Metadata-Version: 2.1
Name: pyramid-oauthlib-lowlevel
Version: 0.4.0
Summary: lowlevel Pyramid implementation of oauthlib
Home-page: https://github.com/jvanasco/pyramid_oauthlib_lowlevel
Author: Jonathan Vanasco
Author-email: jonathan@findmeon.com
License: BSD
Keywords: web pyramid oauth oauthlib
Platform: UNKNOWN
Classifier: Intended Audience :: Developers
Classifier: Framework :: Pyramid
Classifier: Programming Language :: Python
Classifier: Programming Language :: Python :: 3
Classifier: Programming Language :: Python :: 3.7
Classifier: Programming Language :: Python :: 3.8
Classifier: Programming Language :: Python :: 3.9
Classifier: Programming Language :: Python :: 3.10
Classifier: Programming Language :: Python :: 3.11
Classifier: Programming Language :: Python :: 3.12
Classifier: License :: OSI Approved :: BSD License
Provides-Extra: testing
License-File: LICENSE-Pyramid.txt
License-File: LICENSE.txt
